legos.nmap-0.1.0-py3.5-nspkg.pth
legos/nmap.py
legos.nmap-0.1.0.dist-info/DESCRIPTION.rst
legos.nmap-0.1.0.dist-info/METADATA
legos.nmap-0.1.0.dist-info/RECORD
legos.nmap-0.1.0.dist-info/WHEEL
legos.nmap-0.1.0.dist-info/metadata.json
legos.nmap-0.1.0.dist-info/namespace_packages.txt
legos.nmap-0.1.0.dist-info/top_level.txt
